.project
MANIFEST.in
README.txt
bootstrap.py
buildout.cfg
setup.py
collective/__init__.py
collective.contentrules.comingsoon.egg-info/PKG-INFO
collective.contentrules.comingsoon.egg-info/SOURCES.txt
collective.contentrules.comingsoon.egg-info/dependency_links.txt
collective.contentrules.comingsoon.egg-info/entry_points.txt
collective.contentrules.comingsoon.egg-info/namespace_packages.txt
collective.contentrules.comingsoon.egg-info/not-zip-safe
collective.contentrules.comingsoon.egg-info/requires.txt
collective.contentrules.comingsoon.egg-info/top_level.txt
collective/contentrules/__init__.py
collective/contentrules/comingsoon/__init__.py
collective/contentrules/comingsoon/configure.zcml
collective/contentrules/comingsoon/controlpanel.py
collective/contentrules/comingsoon/event.py
collective/contentrules/comingsoon/interfaces.py
collective/contentrules/comingsoon/notify.py
collective/contentrules/comingsoon/tests.py
collective/contentrules/comingsoon/vocabulary.py
collective/contentrules/comingsoon/locales/collective.contentrules.comingsoon.pot
collective/contentrules/comingsoon/locales/plone.pot
collective/contentrules/comingsoon/locales/update.sh
collective/contentrules/comingsoon/locales/fr/LC_MESSAGES/collective.contentrules.comingsoon.po
collective/contentrules/comingsoon/locales/fr/LC_MESSAGES/plone.po
collective/contentrules/comingsoon/profiles/default/controlpanel.xml
collective/contentrules/comingsoon/profiles/default/metadata.xml
collective/contentrules/comingsoon/profiles/default/registry.xml
collective/contentrules/comingsoon/profiles/tests/contentrules.xml
collective/contentrules/comingsoon/profiles/tests/registry.xml
collective/contentrules/comingsoon/upgrades/__init__.py
collective/contentrules/comingsoon/upgrades/configure.zcml
collective/contentrules/comingsoon/upgrades/step.py
collective/contentrules/comingsoon/upgrades/profiles/v1101/registry.xml
docs/HISTORY.txt
docs/INSTALL.txt
docs/LICENSE.GPL
docs/LICENSE.txt