Metadata-Version: 1.1
Name: collective.contentrules.comingsoon
Version: 1.2
Summary: A rule type which is handled when an event, or any content having a start date, will begin tomorrow, or within any delay.
Home-page: http://svn.plone.org/svn/collective/collective.contentrules.comingsoon
Author: Thomas Desvenain
Author-email: thomas.desvenain@gmail.com
License: GPL
Keywords: datetime
Platform: UNKNOWN
Classifier: Framework :: Plone
Classifier: Programming Language :: Python
